LICENSE
README.rst
setup.py
binex_f/__init__.py
binex_f/const.py
binex_f/restapi.py
binex_f/utils.py
binex_f/ws_subscription.py
binex_f.egg-info/PKG-INFO
binex_f.egg-info/SOURCES.txt
binex_f.egg-info/dependency_links.txt
binex_f.egg-info/requires.txt
binex_f.egg-info/top_level.txt
binex_f/ws/__init__.py
binex_f/ws/channels.py
binex_f/ws/mapping.py
binex_f/ws/ws_connection.py