Metadata-Version: 2.1
Name: binex-f
Version: 0.1.1
Summary: An unofficial Python wrapper for the Binance exchange REST API
Home-page: https://github.com/DeepLn/binex_f.git
Author: DeepLn
Author-email: keyjunze@gmail.com
License: UNKNOWN
Platform: UNKNOWN
License-File: LICENSE
